demo/__init__.py
demo/settings.py
demo/urls.py
silent_auction/__init__.py
silent_auction/admin.py
silent_auction/forms.py
silent_auction/models.py
silent_auction/serializers.py
silent_auction/settings.py
silent_auction/__pycache__/__init__.cpython-35.pyc
silent_auction/migrations/0001_initial.py
silent_auction/migrations/__init__.py
silent_auction/tests/__init__.py
silent_auction/tests/test_simple.py
silent_auction/urls/__init__.py
silent_auction/urls/api/__init__.py
silent_auction/urls/api/bid.py
silent_auction/urls/api/bidder.py
silent_auction/urls/api/event.py
silent_auction/urls/api/eventadmin.py
silent_auction/urls/api/item.py
silent_auction/urls/api/seller.py
silent_auction/views/__init__.py
silent_auction/views/api/__init__.py
silent_auction/views/api/bid.py
silent_auction/views/api/bidder.py
silent_auction/views/api/event.py
silent_auction/views/api/eventadmin.py
silent_auction/views/api/item.py
silent_auction/views/api/seller.py
silent_auction-0.1.3.dist-info/DESCRIPTION.rst
silent_auction-0.1.3.dist-info/METADATA
silent_auction-0.1.3.dist-info/RECORD
silent_auction-0.1.3.dist-info/WHEEL
silent_auction-0.1.3.dist-info/metadata.json
silent_auction-0.1.3.dist-info/top_level.txt
